[
 {
  "default_value": null,
  "doc_type": "Supplier",
  "docstatus": 0,
  "doctype": "Property Setter",
  "doctype_or_field": "DocField",
  "field_name": "naming_series",
  "is_system_generated": 1,
  "modified": "2025-07-09 21:17:13.006863",
  "module": null,
  "name": "Supplier-naming_series-reqd",
  "property": "reqd",
  "property_type": "Check",
  "row_name": null,
  "value": "0"
 },
 {
  "default_value": null,
  "doc_type": "Supplier",
  "docstatus": 0,
  "doctype": "Property Setter",
  "doctype_or_field": "DocField",
  "field_name": "naming_series",
  "is_system_generated": 1,
  "modified": "2025-07-09 21:17:13.139302",
  "module": null,
  "name": "Supplier-naming_series-hidden",
  "property": "hidden",
  "property_type": "Check",
  "row_name": null,
  "value": "1"
 },
 {
  "default_value": null,
  "doc_type": "Customer",
  "docstatus": 0,
  "doctype": "Property Setter",
  "doctype_or_field": "DocField",
  "field_name": "naming_series",
  "is_system_generated": 1,
  "modified": "2025-07-09 21:17:13.389100",
  "module": null,
  "name": "Customer-naming_series-reqd",
  "property": "reqd",
  "property_type": "Check",
  "row_name": null,
  "value": "0"
 },
 {
  "default_value": null,
  "doc_type": "Customer",
  "docstatus": 0,
  "doctype": "Property Setter",
  "doctype_or_field": "DocField",
  "field_name": "naming_series",
  "is_system_generated": 1,
  "modified": "2025-07-09 21:17:13.513056",
  "module": null,
  "name": "Customer-naming_series-hidden",
  "property": "hidden",
  "property_type": "Check",
  "row_name": null,
  "value": "1"
 },
 {
  "default_value": null,
  "doc_type": "Sales Order",
  "docstatus": 0,
  "doctype": "Property Setter",
  "doctype_or_field": "DocField",
  "field_name": "tax_id",
  "is_system_generated": 1,
  "modified": "2025-07-09 21:17:13.522166",
  "module": null,
  "name": "Sales Order-tax_id-hidden",
  "property": "hidden",
  "property_type": "Check",
  "row_name": null,
  "value": "0"
 },
 {
  "default_value": null,
  "doc_type": "Sales Order",
  "docstatus": 0,
  "doctype": "Property Setter",
  "doctype_or_field": "DocField",
  "field_name": "tax_id",
  "is_system_generated": 1,
  "modified": "2025-07-09 21:17:13.527069",
  "module": null,
  "name": "Sales Order-tax_id-print_hide",
  "property": "print_hide",
  "property_type": "Check",
  "row_name": null,
  "value": "0"
 },
 {
  "default_value": null,
  "doc_type": "Sales Invoice",
  "docstatus": 0,
  "doctype": "Property Setter",
  "doctype_or_field": "DocField",
  "field_name": "tax_id",
  "is_system_generated": 1,
  "modified": "2025-07-09 21:17:13.532120",
  "module": null,
  "name": "Sales Invoice-tax_id-hidden",
  "property": "hidden",
  "property_type": "Check",
  "row_name": null,
  "value": "0"
 },
 {
  "default_value": null,
  "doc_type": "Sales Invoice",
  "docstatus": 0,
  "doctype": "Property Setter",
  "doctype_or_field": "DocField",
  "field_name": "tax_id",
  "is_system_generated": 1,
  "modified": "2025-07-09 21:17:13.538259",
  "module": null,
  "name": "Sales Invoice-tax_id-print_hide",
  "property": "print_hide",
  "property_type": "Check",
  "row_name": null,
  "value": "0"
 },
 {
  "default_value": null,
  "doc_type": "Delivery Note",
  "docstatus": 0,
  "doctype": "Property Setter",
  "doctype_or_field": "DocField",
  "field_name": "tax_id",
  "is_system_generated": 1,
  "modified": "2025-07-09 21:17:13.543593",
  "module": null,
  "name": "Delivery Note-tax_id-hidden",
  "property": "hidden",
  "property_type": "Check",
  "row_name": null,
  "value": "0"
 },
 {
  "default_value": null,
  "doc_type": "Delivery Note",
  "docstatus": 0,
  "doctype": "Property Setter",
  "doctype_or_field": "DocField",
  "field_name": "tax_id",
  "is_system_generated": 1,
  "modified": "2025-07-09 21:17:13.548912",
  "module": null,
  "name": "Delivery Note-tax_id-print_hide",
  "property": "print_hide",
  "property_type": "Check",
  "row_name": null,
  "value": "0"
 },
 {
  "default_value": null,
  "doc_type": "Packed Item",
  "docstatus": 0,
  "doctype": "Property Setter",
  "doctype_or_field": "DocField",
  "field_name": "rate",
  "is_system_generated": 1,
  "modified": "2025-07-09 21:17:13.553940",
  "module": null,
  "name": "Packed Item-rate-read_only",
  "property": "read_only",
  "property_type": "Check",
  "row_name": null,
  "value": "1"
 },
 {
  "default_value": null,
  "doc_type": "Sales Invoice Item",
  "docstatus": 0,
  "doctype": "Property Setter",
  "doctype_or_field": "DocField",
  "field_name": "discount_account",
  "is_system_generated": 1,
  "modified": "2025-07-09 21:17:13.561449",
  "module": null,
  "name": "Sales Invoice Item-discount_account-hidden",
  "property": "hidden",
  "property_type": "Check",
  "row_name": null,
  "value": "1"
 },
 {
  "default_value": null,
  "doc_type": "Sales Invoice Item",
  "docstatus": 0,
  "doctype": "Property Setter",
  "doctype_or_field": "DocField",
  "field_name": "discount_account",
  "is_system_generated": 1,
  "modified": "2025-07-09 21:17:13.566992",
  "module": null,
  "name": "Sales Invoice Item-discount_account-mandatory_depends_on",
  "property": "mandatory_depends_on",
  "property_type": "Code",
  "row_name": null,
  "value": ""
 },
 {
  "default_value": null,
  "doc_type": "Sales Invoice",
  "docstatus": 0,
  "doctype": "Property Setter",
  "doctype_or_field": "DocField",
  "field_name": "additional_discount_account",
  "is_system_generated": 1,
  "modified": "2025-07-09 21:17:13.572654",
  "module": null,
  "name": "Sales Invoice-additional_discount_account-hidden",
  "property": "hidden",
  "property_type": "Check",
  "row_name": null,
  "value": "1"
 },
 {
  "default_value": null,
  "doc_type": "Sales Invoice",
  "docstatus": 0,
  "doctype": "Property Setter",
  "doctype_or_field": "DocField",
  "field_name": "additional_discount_account",
  "is_system_generated": 1,
  "modified": "2025-07-09 21:17:13.577597",
  "module": null,
  "name": "Sales Invoice-additional_discount_account-mandatory_depends_on",
  "property": "mandatory_depends_on",
  "property_type": "Code",
  "row_name": null,
  "value": ""
 },
 {
  "default_value": null,
  "doc_type": "Quotation",
  "docstatus": 0,
  "doctype": "Property Setter",
  "doctype_or_field": "DocField",
  "field_name": "base_rounded_total",
  "is_system_generated": 1,
  "modified": "2025-07-09 21:17:13.755599",
  "module": null,
  "name": "Quotation-base_rounded_total-hidden",
  "property": "hidden",
  "property_type": "Check",
  "row_name": null,
  "value": "0"
 },
 {
  "default_value": null,
  "doc_type": "Quotation",
  "docstatus": 0,
  "doctype": "Property Setter",
  "doctype_or_field": "DocField",
  "field_name": "base_rounded_total",
  "is_system_generated": 1,
  "modified": "2025-07-09 21:17:13.884898",
  "module": null,
  "name": "Quotation-base_rounded_total-print_hide",
  "property": "print_hide",
  "property_type": "Check",
  "row_name": null,
  "value": "1"
 },
 {
  "default_value": null,
  "doc_type": "Quotation",
  "docstatus": 0,
  "doctype": "Property Setter",
  "doctype_or_field": "DocField",
  "field_name": "rounded_total",
  "is_system_generated": 1,
  "modified": "2025-07-09 21:17:13.890855",
  "module": null,
  "name": "Quotation-rounded_total-hidden",
  "property": "hidden",
  "property_type": "Check",
  "row_name": null,
  "value": "0"
 },
 {
  "default_value": null,
  "doc_type": "Quotation",
  "docstatus": 0,
  "doctype": "Property Setter",
  "doctype_or_field": "DocField",
  "field_name": "rounded_total",
  "is_system_generated": 1,
  "modified": "2025-07-09 21:17:13.897567",
  "module": null,
  "name": "Quotation-rounded_total-print_hide",
  "property": "print_hide",
  "property_type": "Check",
  "row_name": null,
  "value": "0"
 },
 {
  "default_value": null,
  "doc_type": "Quotation",
  "docstatus": 0,
  "doctype": "Property Setter",
  "doctype_or_field": "DocField",
  "field_name": "disable_rounded_total",
  "is_system_generated": 1,
  "modified": "2025-07-09 21:17:13.903672",
  "module": null,
  "name": "Quotation-disable_rounded_total-default",
  "property": "default",
  "property_type": "Text",
  "row_name": null,
  "value": "0"
 },
 {
  "default_value": null,
  "doc_type": "Sales Order",
  "docstatus": 0,
  "doctype": "Property Setter",
  "doctype_or_field": "DocField",
  "field_name": "base_rounded_total",
  "is_system_generated": 1,
  "modified": "2025-07-09 21:17:13.910143",
  "module": null,
  "name": "Sales Order-base_rounded_total-hidden",
  "property": "hidden",
  "property_type": "Check",
  "row_name": null,
  "value": "0"
 },
 {
  "default_value": null,
  "doc_type": "Sales Order",
  "docstatus": 0,
  "doctype": "Property Setter",
  "doctype_or_field": "DocField",
  "field_name": "base_rounded_total",
  "is_system_generated": 1,
  "modified": "2025-07-09 21:17:13.916751",
  "module": null,
  "name": "Sales Order-base_rounded_total-print_hide",
  "property": "print_hide",
  "property_type": "Check",
  "row_name": null,
  "value": "1"
 },
 {
  "default_value": null,
  "doc_type": "Sales Order",
  "docstatus": 0,
  "doctype": "Property Setter",
  "doctype_or_field": "DocField",
  "field_name": "rounded_total",
  "is_system_generated": 1,
  "modified": "2025-07-09 21:17:13.924045",
  "module": null,
  "name": "Sales Order-rounded_total-hidden",
  "property": "hidden",
  "property_type": "Check",
  "row_name": null,
  "value": "0"
 },
 {
  "default_value": null,
  "doc_type": "Sales Order",
  "docstatus": 0,
  "doctype": "Property Setter",
  "doctype_or_field": "DocField",
  "field_name": "rounded_total",
  "is_system_generated": 1,
  "modified": "2025-07-09 21:17:13.931515",
  "module": null,
  "name": "Sales Order-rounded_total-print_hide",
  "property": "print_hide",
  "property_type": "Check",
  "row_name": null,
  "value": "0"
 },
 {
  "default_value": null,
  "doc_type": "Sales Order",
  "docstatus": 0,
  "doctype": "Property Setter",
  "doctype_or_field": "DocField",
  "field_name": "disable_rounded_total",
  "is_system_generated": 1,
  "modified": "2025-07-09 21:17:13.937615",
  "module": null,
  "name": "Sales Order-disable_rounded_total-default",
  "property": "default",
  "property_type": "Text",
  "row_name": null,
  "value": "0"
 },
 {
  "default_value": null,
  "doc_type": "Sales Invoice",
  "docstatus": 0,
  "doctype": "Property Setter",
  "doctype_or_field": "DocField",
  "field_name": "base_rounded_total",
  "is_system_generated": 1,
  "modified": "2025-07-09 21:17:13.943273",
  "module": null,
  "name": "Sales Invoice-base_rounded_total-hidden",
  "property": "hidden",
  "property_type": "Check",
  "row_name": null,
  "value": "0"
 },
 {
  "default_value": null,
  "doc_type": "Sales Invoice",
  "docstatus": 0,
  "doctype": "Property Setter",
  "doctype_or_field": "DocField",
  "field_name": "base_rounded_total",
  "is_system_generated": 1,
  "modified": "2025-07-09 21:17:13.950618",
  "module": null,
  "name": "Sales Invoice-base_rounded_total-print_hide",
  "property": "print_hide",
  "property_type": "Check",
  "row_name": null,
  "value": "1"
 },
 {
  "default_value": null,
  "doc_type": "Sales Invoice",
  "docstatus": 0,
  "doctype": "Property Setter",
  "doctype_or_field": "DocField",
  "field_name": "rounded_total",
  "is_system_generated": 1,
  "modified": "2025-07-09 21:17:13.956437",
  "module": null,
  "name": "Sales Invoice-rounded_total-hidden",
  "property": "hidden",
  "property_type": "Check",
  "row_name": null,
  "value": "0"
 },
 {
  "default_value": null,
  "doc_type": "Sales Invoice",
  "docstatus": 0,
  "doctype": "Property Setter",
  "doctype_or_field": "DocField",
  "field_name": "rounded_total",
  "is_system_generated": 1,
  "modified": "2025-07-09 21:17:13.962206",
  "module": null,
  "name": "Sales Invoice-rounded_total-print_hide",
  "property": "print_hide",
  "property_type": "Check",
  "row_name": null,
  "value": "0"
 },
 {
  "default_value": null,
  "doc_type": "Sales Invoice",
  "docstatus": 0,
  "doctype": "Property Setter",
  "doctype_or_field": "DocField",
  "field_name": "disable_rounded_total",
  "is_system_generated": 1,
  "modified": "2025-07-09 21:17:13.967870",
  "module": null,
  "name": "Sales Invoice-disable_rounded_total-default",
  "property": "default",
  "property_type": "Text",
  "row_name": null,
  "value": "0"
 },
 {
  "default_value": null,
  "doc_type": "Delivery Note",
  "docstatus": 0,
  "doctype": "Property Setter",
  "doctype_or_field": "DocField",
  "field_name": "base_rounded_total",
  "is_system_generated": 1,
  "modified": "2025-07-09 21:17:13.973615",
  "module": null,
  "name": "Delivery Note-base_rounded_total-hidden",
  "property": "hidden",
  "property_type": "Check",
  "row_name": null,
  "value": "0"
 },
 {
  "default_value": null,
  "doc_type": "Delivery Note",
  "docstatus": 0,
  "doctype": "Property Setter",
  "doctype_or_field": "DocField",
  "field_name": "base_rounded_total",
  "is_system_generated": 1,
  "modified": "2025-07-09 21:17:13.979349",
  "module": null,
  "name": "Delivery Note-base_rounded_total-print_hide",
  "property": "print_hide",
  "property_type": "Check",
  "row_name": null,
  "value": "1"
 },
 {
  "default_value": null,
  "doc_type": "Delivery Note",
  "docstatus": 0,
  "doctype": "Property Setter",
  "doctype_or_field": "DocField",
  "field_name": "rounded_total",
  "is_system_generated": 1,
  "modified": "2025-07-09 21:17:13.984960",
  "module": null,
  "name": "Delivery Note-rounded_total-hidden",
  "property": "hidden",
  "property_type": "Check",
  "row_name": null,
  "value": "0"
 },
 {
  "default_value": null,
  "doc_type": "Delivery Note",
  "docstatus": 0,
  "doctype": "Property Setter",
  "doctype_or_field": "DocField",
  "field_name": "rounded_total",
  "is_system_generated": 1,
  "modified": "2025-07-09 21:17:13.990476",
  "module": null,
  "name": "Delivery Note-rounded_total-print_hide",
  "property": "print_hide",
  "property_type": "Check",
  "row_name": null,
  "value": "0"
 },
 {
  "default_value": null,
  "doc_type": "Delivery Note",
  "docstatus": 0,
  "doctype": "Property Setter",
  "doctype_or_field": "DocField",
  "field_name": "disable_rounded_total",
  "is_system_generated": 1,
  "modified": "2025-07-09 21:17:13.995448",
  "module": null,
  "name": "Delivery Note-disable_rounded_total-default",
  "property": "default",
  "property_type": "Text",
  "row_name": null,
  "value": "0"
 },
 {
  "default_value": null,
  "doc_type": "Supplier Quotation",
  "docstatus": 0,
  "doctype": "Property Setter",
  "doctype_or_field": "DocField",
  "field_name": "base_rounded_total",
  "is_system_generated": 1,
  "modified": "2025-07-09 21:17:14.000064",
  "module": null,
  "name": "Supplier Quotation-base_rounded_total-hidden",
  "property": "hidden",
  "property_type": "Check",
  "row_name": null,
  "value": "0"
 },
 {
  "default_value": null,
  "doc_type": "Supplier Quotation",
  "docstatus": 0,
  "doctype": "Property Setter",
  "doctype_or_field": "DocField",
  "field_name": "base_rounded_total",
  "is_system_generated": 1,
  "modified": "2025-07-09 21:17:14.004855",
  "module": null,
  "name": "Supplier Quotation-base_rounded_total-print_hide",
  "property": "print_hide",
  "property_type": "Check",
  "row_name": null,
  "value": "1"
 },
 {
  "default_value": null,
  "doc_type": "Supplier Quotation",
  "docstatus": 0,
  "doctype": "Property Setter",
  "doctype_or_field": "DocField",
  "field_name": "rounded_total",
  "is_system_generated": 1,
  "modified": "2025-07-09 21:17:14.009391",
  "module": null,
  "name": "Supplier Quotation-rounded_total-hidden",
  "property": "hidden",
  "property_type": "Check",
  "row_name": null,
  "value": "0"
 },
 {
  "default_value": null,
  "doc_type": "Supplier Quotation",
  "docstatus": 0,
  "doctype": "Property Setter",
  "doctype_or_field": "DocField",
  "field_name": "rounded_total",
  "is_system_generated": 1,
  "modified": "2025-07-09 21:17:14.014063",
  "module": null,
  "name": "Supplier Quotation-rounded_total-print_hide",
  "property": "print_hide",
  "property_type": "Check",
  "row_name": null,
  "value": "0"
 },
 {
  "default_value": null,
  "doc_type": "Supplier Quotation",
  "docstatus": 0,
  "doctype": "Property Setter",
  "doctype_or_field": "DocField",
  "field_name": "disable_rounded_total",
  "is_system_generated": 1,
  "modified": "2025-07-09 21:17:14.018819",
  "module": null,
  "name": "Supplier Quotation-disable_rounded_total-default",
  "property": "default",
  "property_type": "Text",
  "row_name": null,
  "value": "0"
 },
 {
  "default_value": null,
  "doc_type": "Purchase Order",
  "docstatus": 0,
  "doctype": "Property Setter",
  "doctype_or_field": "DocField",
  "field_name": "base_rounded_total",
  "is_system_generated": 1,
  "modified": "2025-07-09 21:17:14.023490",
  "module": null,
  "name": "Purchase Order-base_rounded_total-hidden",
  "property": "hidden",
  "property_type": "Check",
  "row_name": null,
  "value": "0"
 },
 {
  "default_value": null,
  "doc_type": "Purchase Order",
  "docstatus": 0,
  "doctype": "Property Setter",
  "doctype_or_field": "DocField",
  "field_name": "base_rounded_total",
  "is_system_generated": 1,
  "modified": "2025-07-09 21:17:14.028108",
  "module": null,
  "name": "Purchase Order-base_rounded_total-print_hide",
  "property": "print_hide",
  "property_type": "Check",
  "row_name": null,
  "value": "1"
 },
 {
  "default_value": null,
  "doc_type": "Purchase Order",
  "docstatus": 0,
  "doctype": "Property Setter",
  "doctype_or_field": "DocField",
  "field_name": "rounded_total",
  "is_system_generated": 1,
  "modified": "2025-07-09 21:17:14.032670",
  "module": null,
  "name": "Purchase Order-rounded_total-hidden",
  "property": "hidden",
  "property_type": "Check",
  "row_name": null,
  "value": "0"
 },
 {
  "default_value": null,
  "doc_type": "Purchase Order",
  "docstatus": 0,
  "doctype": "Property Setter",
  "doctype_or_field": "DocField",
  "field_name": "rounded_total",
  "is_system_generated": 1,
  "modified": "2025-07-09 21:17:14.037690",
  "module": null,
  "name": "Purchase Order-rounded_total-print_hide",
  "property": "print_hide",
  "property_type": "Check",
  "row_name": null,
  "value": "0"
 },
 {
  "default_value": null,
  "doc_type": "Purchase Order",
  "docstatus": 0,
  "doctype": "Property Setter",
  "doctype_or_field": "DocField",
  "field_name": "disable_rounded_total",
  "is_system_generated": 1,
  "modified": "2025-07-09 21:17:14.043095",
  "module": null,
  "name": "Purchase Order-disable_rounded_total-default",
  "property": "default",
  "property_type": "Text",
  "row_name": null,
  "value": "0"
 },
 {
  "default_value": null,
  "doc_type": "Purchase Invoice",
  "docstatus": 0,
  "doctype": "Property Setter",
  "doctype_or_field": "DocField",
  "field_name": "base_rounded_total",
  "is_system_generated": 1,
  "modified": "2025-07-09 21:17:14.047879",
  "module": null,
  "name": "Purchase Invoice-base_rounded_total-hidden",
  "property": "hidden",
  "property_type": "Check",
  "row_name": null,
  "value": "0"
 },
 {
  "default_value": null,
  "doc_type": "Purchase Invoice",
  "docstatus": 0,
  "doctype": "Property Setter",
  "doctype_or_field": "DocField",
  "field_name": "base_rounded_total",
  "is_system_generated": 1,
  "modified": "2025-07-09 21:17:14.052916",
  "module": null,
  "name": "Purchase Invoice-base_rounded_total-print_hide",
  "property": "print_hide",
  "property_type": "Check",
  "row_name": null,
  "value": "1"
 },
 {
  "default_value": null,
  "doc_type": "Purchase Invoice",
  "docstatus": 0,
  "doctype": "Property Setter",
  "doctype_or_field": "DocField",
  "field_name": "rounded_total",
  "is_system_generated": 1,
  "modified": "2025-07-09 21:17:14.058352",
  "module": null,
  "name": "Purchase Invoice-rounded_total-hidden",
  "property": "hidden",
  "property_type": "Check",
  "row_name": null,
  "value": "0"
 },
 {
  "default_value": null,
  "doc_type": "Purchase Invoice",
  "docstatus": 0,
  "doctype": "Property Setter",
  "doctype_or_field": "DocField",
  "field_name": "rounded_total",
  "is_system_generated": 1,
  "modified": "2025-07-09 21:17:14.063378",
  "module": null,
  "name": "Purchase Invoice-rounded_total-print_hide",
  "property": "print_hide",
  "property_type": "Check",
  "row_name": null,
  "value": "0"
 },
 {
  "default_value": null,
  "doc_type": "Purchase Invoice",
  "docstatus": 0,
  "doctype": "Property Setter",
  "doctype_or_field": "DocField",
  "field_name": "disable_rounded_total",
  "is_system_generated": 1,
  "modified": "2025-07-09 21:17:14.068387",
  "module": null,
  "name": "Purchase Invoice-disable_rounded_total-default",
  "property": "default",
  "property_type": "Text",
  "row_name": null,
  "value": "0"
 },
 {
  "default_value": null,
  "doc_type": "Purchase Receipt",
  "docstatus": 0,
  "doctype": "Property Setter",
  "doctype_or_field": "DocField",
  "field_name": "base_rounded_total",
  "is_system_generated": 1,
  "modified": "2025-07-09 21:17:14.073347",
  "module": null,
  "name": "Purchase Receipt-base_rounded_total-hidden",
  "property": "hidden",
  "property_type": "Check",
  "row_name": null,
  "value": "0"
 },
 {
  "default_value": null,
  "doc_type": "Purchase Receipt",
  "docstatus": 0,
  "doctype": "Property Setter",
  "doctype_or_field": "DocField",
  "field_name": "base_rounded_total",
  "is_system_generated": 1,
  "modified": "2025-07-09 21:17:14.078274",
  "module": null,
  "name": "Purchase Receipt-base_rounded_total-print_hide",
  "property": "print_hide",
  "property_type": "Check",
  "row_name": null,
  "value": "1"
 },
 {
  "default_value": null,
  "doc_type": "Purchase Receipt",
  "docstatus": 0,
  "doctype": "Property Setter",
  "doctype_or_field": "DocField",
  "field_name": "rounded_total",
  "is_system_generated": 1,
  "modified": "2025-07-09 21:17:14.083086",
  "module": null,
  "name": "Purchase Receipt-rounded_total-hidden",
  "property": "hidden",
  "property_type": "Check",
  "row_name": null,
  "value": "0"
 },
 {
  "default_value": null,
  "doc_type": "Purchase Receipt",
  "docstatus": 0,
  "doctype": "Property Setter",
  "doctype_or_field": "DocField",
  "field_name": "rounded_total",
  "is_system_generated": 1,
  "modified": "2025-07-09 21:17:14.087873",
  "module": null,
  "name": "Purchase Receipt-rounded_total-print_hide",
  "property": "print_hide",
  "property_type": "Check",
  "row_name": null,
  "value": "0"
 },
 {
  "default_value": null,
  "doc_type": "Purchase Receipt",
  "docstatus": 0,
  "doctype": "Property Setter",
  "doctype_or_field": "DocField",
  "field_name": "disable_rounded_total",
  "is_system_generated": 1,
  "modified": "2025-07-09 21:17:14.092604",
  "module": null,
  "name": "Purchase Receipt-disable_rounded_total-default",
  "property": "default",
  "property_type": "Text",
  "row_name": null,
  "value": "0"
 },
 {
  "default_value": null,
  "doc_type": "Quotation",
  "docstatus": 0,
  "doctype": "Property Setter",
  "doctype_or_field": "DocField",
  "field_name": "in_words",
  "is_system_generated": 1,
  "modified": "2025-07-09 21:17:14.097225",
  "module": null,
  "name": "Quotation-in_words-hidden",
  "property": "hidden",
  "property_type": "Check",
  "row_name": null,
  "value": "0"
 },
 {
  "default_value": null,
  "doc_type": "Quotation",
  "docstatus": 0,
  "doctype": "Property Setter",
  "doctype_or_field": "DocField",
  "field_name": "in_words",
  "is_system_generated": 1,
  "modified": "2025-07-09 21:17:14.101920",
  "module": null,
  "name": "Quotation-in_words-print_hide",
  "property": "print_hide",
  "property_type": "Check",
  "row_name": null,
  "value": "0"
 },
 {
  "default_value": null,
  "doc_type": "Sales Order",
  "docstatus": 0,
  "doctype": "Property Setter",
  "doctype_or_field": "DocField",
  "field_name": "in_words",
  "is_system_generated": 1,
  "modified": "2025-07-09 21:17:14.106937",
  "module": null,
  "name": "Sales Order-in_words-hidden",
  "property": "hidden",
  "property_type": "Check",
  "row_name": null,
  "value": "0"
 },
 {
  "default_value": null,
  "doc_type": "Sales Order",
  "docstatus": 0,
  "doctype": "Property Setter",
  "doctype_or_field": "DocField",
  "field_name": "in_words",
  "is_system_generated": 1,
  "modified": "2025-07-09 21:17:14.111736",
  "module": null,
  "name": "Sales Order-in_words-print_hide",
  "property": "print_hide",
  "property_type": "Check",
  "row_name": null,
  "value": "0"
 },
 {
  "default_value": null,
  "doc_type": "Sales Invoice",
  "docstatus": 0,
  "doctype": "Property Setter",
  "doctype_or_field": "DocField",
  "field_name": "in_words",
  "is_system_generated": 1,
  "modified": "2025-07-09 21:17:14.116351",
  "module": null,
  "name": "Sales Invoice-in_words-hidden",
  "property": "hidden",
  "property_type": "Check",
  "row_name": null,
  "value": "0"
 },
 {
  "default_value": null,
  "doc_type": "Sales Invoice",
  "docstatus": 0,
  "doctype": "Property Setter",
  "doctype_or_field": "DocField",
  "field_name": "in_words",
  "is_system_generated": 1,
  "modified": "2025-07-09 21:17:14.121041",
  "module": null,
  "name": "Sales Invoice-in_words-print_hide",
  "property": "print_hide",
  "property_type": "Check",
  "row_name": null,
  "value": "0"
 },
 {
  "default_value": null,
  "doc_type": "Delivery Note",
  "docstatus": 0,
  "doctype": "Property Setter",
  "doctype_or_field": "DocField",
  "field_name": "in_words",
  "is_system_generated": 1,
  "modified": "2025-07-09 21:17:14.125716",
  "module": null,
  "name": "Delivery Note-in_words-hidden",
  "property": "hidden",
  "property_type": "Check",
  "row_name": null,
  "value": "0"
 },
 {
  "default_value": null,
  "doc_type": "Delivery Note",
  "docstatus": 0,
  "doctype": "Property Setter",
  "doctype_or_field": "DocField",
  "field_name": "in_words",
  "is_system_generated": 1,
  "modified": "2025-07-09 21:17:14.130445",
  "module": null,
  "name": "Delivery Note-in_words-print_hide",
  "property": "print_hide",
  "property_type": "Check",
  "row_name": null,
  "value": "0"
 },
 {
  "default_value": null,
  "doc_type": "Supplier Quotation",
  "docstatus": 0,
  "doctype": "Property Setter",
  "doctype_or_field": "DocField",
  "field_name": "in_words",
  "is_system_generated": 1,
  "modified": "2025-07-09 21:17:14.135226",
  "module": null,
  "name": "Supplier Quotation-in_words-hidden",
  "property": "hidden",
  "property_type": "Check",
  "row_name": null,
  "value": "0"
 },
 {
  "default_value": null,
  "doc_type": "Supplier Quotation",
  "docstatus": 0,
  "doctype": "Property Setter",
  "doctype_or_field": "DocField",
  "field_name": "in_words",
  "is_system_generated": 1,
  "modified": "2025-07-09 21:17:14.140063",
  "module": null,
  "name": "Supplier Quotation-in_words-print_hide",
  "property": "print_hide",
  "property_type": "Check",
  "row_name": null,
  "value": "0"
 },
 {
  "default_value": null,
  "doc_type": "Purchase Order",
  "docstatus": 0,
  "doctype": "Property Setter",
  "doctype_or_field": "DocField",
  "field_name": "in_words",
  "is_system_generated": 1,
  "modified": "2025-07-09 21:17:14.144721",
  "module": null,
  "name": "Purchase Order-in_words-hidden",
  "property": "hidden",
  "property_type": "Check",
  "row_name": null,
  "value": "0"
 },
 {
  "default_value": null,
  "doc_type": "Purchase Order",
  "docstatus": 0,
  "doctype": "Property Setter",
  "doctype_or_field": "DocField",
  "field_name": "in_words",
  "is_system_generated": 1,
  "modified": "2025-07-09 21:17:14.149762",
  "module": null,
  "name": "Purchase Order-in_words-print_hide",
  "property": "print_hide",
  "property_type": "Check",
  "row_name": null,
  "value": "0"
 },
 {
  "default_value": null,
  "doc_type": "Purchase Invoice",
  "docstatus": 0,
  "doctype": "Property Setter",
  "doctype_or_field": "DocField",
  "field_name": "in_words",
  "is_system_generated": 1,
  "modified": "2025-07-09 21:17:14.154760",
  "module": null,
  "name": "Purchase Invoice-in_words-hidden",
  "property": "hidden",
  "property_type": "Check",
  "row_name": null,
  "value": "0"
 },
 {
  "default_value": null,
  "doc_type": "Purchase Invoice",
  "docstatus": 0,
  "doctype": "Property Setter",
  "doctype_or_field": "DocField",
  "field_name": "in_words",
  "is_system_generated": 1,
  "modified": "2025-07-09 21:17:14.159517",
  "module": null,
  "name": "Purchase Invoice-in_words-print_hide",
  "property": "print_hide",
  "property_type": "Check",
  "row_name": null,
  "value": "0"
 },
 {
  "default_value": null,
  "doc_type": "Purchase Receipt",
  "docstatus": 0,
  "doctype": "Property Setter",
  "doctype_or_field": "DocField",
  "field_name": "in_words",
  "is_system_generated": 1,
  "modified": "2025-07-09 21:17:14.164131",
  "module": null,
  "name": "Purchase Receipt-in_words-hidden",
  "property": "hidden",
  "property_type": "Check",
  "row_name": null,
  "value": "0"
 },
 {
  "default_value": null,
  "doc_type": "Purchase Receipt",
  "docstatus": 0,
  "doctype": "Property Setter",
  "doctype_or_field": "DocField",
  "field_name": "in_words",
  "is_system_generated": 1,
  "modified": "2025-07-09 21:17:14.168899",
  "module": null,
  "name": "Purchase Receipt-in_words-print_hide",
  "property": "print_hide",
  "property_type": "Check",
  "row_name": null,
  "value": "0"
 },
 {
  "default_value": null,
  "doc_type": "Item",
  "docstatus": 0,
  "doctype": "Property Setter",
  "doctype_or_field": "DocField",
  "field_name": "naming_series",
  "is_system_generated": 1,
  "modified": "2025-07-09 21:17:14.776997",
  "module": null,
  "name": "Item-naming_series-reqd",
  "property": "reqd",
  "property_type": "Check",
  "row_name": null,
  "value": "0"
 },
 {
  "default_value": null,
  "doc_type": "Item",
  "docstatus": 0,
  "doctype": "Property Setter",
  "doctype_or_field": "DocField",
  "field_name": "naming_series",
  "is_system_generated": 1,
  "modified": "2025-07-09 21:17:14.903636",
  "module": null,
  "name": "Item-naming_series-hidden",
  "property": "hidden",
  "property_type": "Check",
  "row_name": null,
  "value": "1"
 },
 {
  "default_value": null,
  "doc_type": "Item",
  "docstatus": 0,
  "doctype": "Property Setter",
  "doctype_or_field": "DocField",
  "field_name": "item_code",
  "is_system_generated": 1,
  "modified": "2025-07-09 21:17:14.908632",
  "module": null,
  "name": "Item-item_code-hidden",
  "property": "hidden",
  "property_type": "Check",
  "row_name": null,
  "value": "0"
 },
 {
  "default_value": null,
  "doc_type": "Item",
  "docstatus": 0,
  "doctype": "Property Setter",
  "doctype_or_field": "DocField",
  "field_name": "item_code",
  "is_system_generated": 1,
  "modified": "2025-07-09 21:17:14.913592",
  "module": null,
  "name": "Item-item_code-reqd",
  "property": "reqd",
  "property_type": "Check",
  "row_name": null,
  "value": "1"
 },
 {
  "default_value": null,
  "doc_type": "Sales Invoice Item",
  "docstatus": 0,
  "doctype": "Property Setter",
  "doctype_or_field": "DocField",
  "field_name": "barcode",
  "is_system_generated": 1,
  "modified": "2025-07-09 21:17:14.922104",
  "module": null,
  "name": "Sales Invoice Item-barcode-hidden",
  "property": "hidden",
  "property_type": "Check",
  "row_name": null,
  "value": "0"
 },
 {
  "default_value": null,
  "doc_type": "POS Invoice Item",
  "docstatus": 0,
  "doctype": "Property Setter",
  "doctype_or_field": "DocField",
  "field_name": "barcode",
  "is_system_generated": 1,
  "modified": "2025-07-09 21:17:14.927416",
  "module": null,
  "name": "POS Invoice Item-barcode-hidden",
  "property": "hidden",
  "property_type": "Check",
  "row_name": null,
  "value": "0"
 },
 {
  "default_value": null,
  "doc_type": "Job Card",
  "docstatus": 0,
  "doctype": "Property Setter",
  "doctype_or_field": "DocField",
  "field_name": "barcode",
  "is_system_generated": 1,
  "modified": "2025-07-09 21:17:14.933013",
  "module": null,
  "name": "Job Card-barcode-hidden",
  "property": "hidden",
  "property_type": "Check",
  "row_name": null,
  "value": "0"
 },
 {
  "default_value": null,
  "doc_type": "Item Barcode",
  "docstatus": 0,
  "doctype": "Property Setter",
  "doctype_or_field": "DocField",
  "field_name": "barcode",
  "is_system_generated": 1,
  "modified": "2025-07-09 21:17:14.938100",
  "module": null,
  "name": "Item Barcode-barcode-hidden",
  "property": "hidden",
  "property_type": "Check",
  "row_name": null,
  "value": "0"
 },
 {
  "default_value": null,
  "doc_type": "Stock Entry Detail",
  "docstatus": 0,
  "doctype": "Property Setter",
  "doctype_or_field": "DocField",
  "field_name": "barcode",
  "is_system_generated": 1,
  "modified": "2025-07-09 21:17:14.943660",
  "module": null,
  "name": "Stock Entry Detail-barcode-hidden",
  "property": "hidden",
  "property_type": "Check",
  "row_name": null,
  "value": "0"
 },
 {
  "default_value": null,
  "doc_type": "Delivery Note Item",
  "docstatus": 0,
  "doctype": "Property Setter",
  "doctype_or_field": "DocField",
  "field_name": "barcode",
  "is_system_generated": 1,
  "modified": "2025-07-09 21:17:14.949531",
  "module": null,
  "name": "Delivery Note Item-barcode-hidden",
  "property": "hidden",
  "property_type": "Check",
  "row_name": null,
  "value": "0"
 },
 {
  "default_value": null,
  "doc_type": "Purchase Receipt Item",
  "docstatus": 0,
  "doctype": "Property Setter",
  "doctype_or_field": "DocField",
  "field_name": "barcode",
  "is_system_generated": 1,
  "modified": "2025-07-09 21:17:14.955043",
  "module": null,
  "name": "Purchase Receipt Item-barcode-hidden",
  "property": "hidden",
  "property_type": "Check",
  "row_name": null,
  "value": "0"
 },
 {
  "default_value": null,
  "doc_type": "Stock Reconciliation Item",
  "docstatus": 0,
  "doctype": "Property Setter",
  "doctype_or_field": "DocField",
  "field_name": "barcode",
  "is_system_generated": 1,
  "modified": "2025-07-09 21:17:14.960711",
  "module": null,
  "name": "Stock Reconciliation Item-barcode-hidden",
  "property": "hidden",
  "property_type": "Check",
  "row_name": null,
  "value": "0"
 },
 {
  "default_value": null,
  "doc_type": "Item",
  "docstatus": 0,
  "doctype": "Property Setter",
  "doctype_or_field": "DocField",
  "field_name": "barcodes",
  "is_system_generated": 1,
  "modified": "2025-07-09 21:17:14.966930",
  "module": null,
  "name": "Item-barcodes-hidden",
  "property": "hidden",
  "property_type": "Check",
  "row_name": null,
  "value": "0"
 },
 {
  "default_value": null,
  "doc_type": "POS Invoice",
  "docstatus": 0,
  "doctype": "Property Setter",
  "doctype_or_field": "DocField",
  "field_name": "scan_barcode",
  "is_system_generated": 1,
  "modified": "2025-07-09 21:17:14.972284",
  "module": null,
  "name": "POS Invoice-scan_barcode-hidden",
  "property": "hidden",
  "property_type": "Check",
  "row_name": null,
  "value": "0"
 },
 {
  "default_value": null,
  "doc_type": "Purchase Invoice",
  "docstatus": 0,
  "doctype": "Property Setter",
  "doctype_or_field": "DocField",
  "field_name": "scan_barcode",
  "is_system_generated": 1,
  "modified": "2025-07-09 21:17:14.977192",
  "module": null,
  "name": "Purchase Invoice-scan_barcode-hidden",
  "property": "hidden",
  "property_type": "Check",
  "row_name": null,
  "value": "0"
 },
 {
  "default_value": null,
  "doc_type": "Sales Invoice",
  "docstatus": 0,
  "doctype": "Property Setter",
  "doctype_or_field": "DocField",
  "field_name": "scan_barcode",
  "is_system_generated": 1,
  "modified": "2025-07-09 21:17:14.981907",
  "module": null,
  "name": "Sales Invoice-scan_barcode-hidden",
  "property": "hidden",
  "property_type": "Check",
  "row_name": null,
  "value": "0"
 },
 {
  "default_value": null,
  "doc_type": "Purchase Order",
  "docstatus": 0,
  "doctype": "Property Setter",
  "doctype_or_field": "DocField",
  "field_name": "scan_barcode",
  "is_system_generated": 1,
  "modified": "2025-07-09 21:17:14.986580",
  "module": null,
  "name": "Purchase Order-scan_barcode-hidden",
  "property": "hidden",
  "property_type": "Check",
  "row_name": null,
  "value": "0"
 },
 {
  "default_value": null,
  "doc_type": "Sales Order",
  "docstatus": 0,
  "doctype": "Property Setter",
  "doctype_or_field": "DocField",
  "field_name": "scan_barcode",
  "is_system_generated": 1,
  "modified": "2025-07-09 21:17:14.991701",
  "module": null,
  "name": "Sales Order-scan_barcode-hidden",
  "property": "hidden",
  "property_type": "Check",
  "row_name": null,
  "value": "0"
 },
 {
  "default_value": null,
  "doc_type": "Quotation",
  "docstatus": 0,
  "doctype": "Property Setter",
  "doctype_or_field": "DocField",
  "field_name": "scan_barcode",
  "is_system_generated": 1,
  "modified": "2025-07-09 21:17:14.996785",
  "module": null,
  "name": "Quotation-scan_barcode-hidden",
  "property": "hidden",
  "property_type": "Check",
  "row_name": null,
  "value": "0"
 },
 {
  "default_value": null,
  "doc_type": "Stock Entry",
  "docstatus": 0,
  "doctype": "Property Setter",
  "doctype_or_field": "DocField",
  "field_name": "scan_barcode",
  "is_system_generated": 1,
  "modified": "2025-07-09 21:17:15.001784",
  "module": null,
  "name": "Stock Entry-scan_barcode-hidden",
  "property": "hidden",
  "property_type": "Check",
  "row_name": null,
  "value": "0"
 },
 {
  "default_value": null,
  "doc_type": "Material Request",
  "docstatus": 0,
  "doctype": "Property Setter",
  "doctype_or_field": "DocField",
  "field_name": "scan_barcode",
  "is_system_generated": 1,
  "modified": "2025-07-09 21:17:15.008795",
  "module": null,
  "name": "Material Request-scan_barcode-hidden",
  "property": "hidden",
  "property_type": "Check",
  "row_name": null,
  "value": "0"
 },
 {
  "default_value": null,
  "doc_type": "Delivery Note",
  "docstatus": 0,
  "doctype": "Property Setter",
  "doctype_or_field": "DocField",
  "field_name": "scan_barcode",
  "is_system_generated": 1,
  "modified": "2025-07-09 21:17:15.014545",
  "module": null,
  "name": "Delivery Note-scan_barcode-hidden",
  "property": "hidden",
  "property_type": "Check",
  "row_name": null,
  "value": "0"
 },
 {
  "default_value": null,
  "doc_type": "Stock Reconciliation",
  "docstatus": 0,
  "doctype": "Property Setter",
  "doctype_or_field": "DocField",
  "field_name": "scan_barcode",
  "is_system_generated": 1,
  "modified": "2025-07-09 21:17:15.020360",
  "module": null,
  "name": "Stock Reconciliation-scan_barcode-hidden",
  "property": "hidden",
  "property_type": "Check",
  "row_name": null,
  "value": "0"
 },
 {
  "default_value": null,
  "doc_type": "Pick List",
  "docstatus": 0,
  "doctype": "Property Setter",
  "doctype_or_field": "DocField",
  "field_name": "scan_barcode",
  "is_system_generated": 1,
  "modified": "2025-07-09 21:17:15.026677",
  "module": null,
  "name": "Pick List-scan_barcode-hidden",
  "property": "hidden",
  "property_type": "Check",
  "row_name": null,
  "value": "0"
 },
 {
  "default_value": null,
  "doc_type": "Purchase Receipt",
  "docstatus": 0,
  "doctype": "Property Setter",
  "doctype_or_field": "DocField",
  "field_name": "scan_barcode",
  "is_system_generated": 1,
  "modified": "2025-07-09 21:17:15.032876",
  "module": null,
  "name": "Purchase Receipt-scan_barcode-hidden",
  "property": "hidden",
  "property_type": "Check",
  "row_name": null,
  "value": "0"
 },
 {
  "default_value": null,
  "doc_type": "Sales Invoice Item",
  "docstatus": 0,
  "doctype": "Property Setter",
  "doctype_or_field": "DocField",
  "field_name": "target_warehouse",
  "is_system_generated": 1,
  "modified": "2025-07-09 21:17:15.053643",
  "module": null,
  "name": "Sales Invoice Item-target_warehouse-hidden",
  "property": "hidden",
  "property_type": "Check",
  "row_name": null,
  "value": "1"
 },
 {
  "default_value": null,
  "doc_type": "Delivery Note Item",
  "docstatus": 0,
  "doctype": "Property Setter",
  "doctype_or_field": "DocField",
  "field_name": "target_warehouse",
  "is_system_generated": 1,
  "modified": "2025-07-09 21:17:15.061085",
  "module": null,
  "name": "Delivery Note Item-target_warehouse-hidden",
  "property": "hidden",
  "property_type": "Check",
  "row_name": null,
  "value": "1"
 },
 {
  "default_value": null,
  "doc_type": "Purchase Invoice Item",
  "docstatus": 0,
  "doctype": "Property Setter",
  "doctype_or_field": "DocField",
  "field_name": "from_warehouse",
  "is_system_generated": 1,
  "modified": "2025-07-09 21:17:15.068120",
  "module": null,
  "name": "Purchase Invoice Item-from_warehouse-hidden",
  "property": "hidden",
  "property_type": "Check",
  "row_name": null,
  "value": "1"
 },
 {
  "default_value": null,
  "doc_type": "Purchase Receipt Item",
  "docstatus": 0,
  "doctype": "Property Setter",
  "doctype_or_field": "DocField",
  "field_name": "from_warehouse",
  "is_system_generated": 1,
  "modified": "2025-07-09 21:17:15.075062",
  "module": null,
  "name": "Purchase Receipt Item-from_warehouse-hidden",
  "property": "hidden",
  "property_type": "Check",
  "row_name": null,
  "value": "1"
 },
 {
  "default_value": null,
  "doc_type": "Sales Order",
  "docstatus": 0,
  "doctype": "Property Setter",
  "doctype_or_field": "DocField",
  "field_name": "due_date",
  "is_system_generated": 1,
  "modified": "2025-07-09 23:29:42.630244",
  "module": null,
  "name": "Sales Order-due_date-print_hide",
  "property": "print_hide",
  "property_type": "Check",
  "row_name": null,
  "value": "0"
 },
 {
  "default_value": null,
  "doc_type": "Sales Order",
  "docstatus": 0,
  "doctype": "Property Setter",
  "doctype_or_field": "DocField",
  "field_name": "payment_schedule",
  "is_system_generated": 1,
  "modified": "2025-07-09 23:29:42.635432",
  "module": null,
  "name": "Sales Order-payment_schedule-print_hide",
  "property": "print_hide",
  "property_type": "Check",
  "row_name": null,
  "value": "1"
 },
 {
  "default_value": null,
  "doc_type": "Sales Invoice",
  "docstatus": 0,
  "doctype": "Property Setter",
  "doctype_or_field": "DocField",
  "field_name": "due_date",
  "is_system_generated": 1,
  "modified": "2025-07-09 23:29:42.639529",
  "module": null,
  "name": "Sales Invoice-due_date-print_hide",
  "property": "print_hide",
  "property_type": "Check",
  "row_name": null,
  "value": "0"
 },
 {
  "default_value": null,
  "doc_type": "Sales Invoice",
  "docstatus": 0,
  "doctype": "Property Setter",
  "doctype_or_field": "DocField",
  "field_name": "payment_schedule",
  "is_system_generated": 1,
  "modified": "2025-07-09 23:29:42.644285",
  "module": null,
  "name": "Sales Invoice-payment_schedule-print_hide",
  "property": "print_hide",
  "property_type": "Check",
  "row_name": null,
  "value": "1"
 },
 {
  "default_value": null,
  "doc_type": "Purchase Order",
  "docstatus": 0,
  "doctype": "Property Setter",
  "doctype_or_field": "DocField",
  "field_name": "due_date",
  "is_system_generated": 1,
  "modified": "2025-07-09 23:29:42.648683",
  "module": null,
  "name": "Purchase Order-due_date-print_hide",
  "property": "print_hide",
  "property_type": "Check",
  "row_name": null,
  "value": "0"
 },
 {
  "default_value": null,
  "doc_type": "Purchase Order",
  "docstatus": 0,
  "doctype": "Property Setter",
  "doctype_or_field": "DocField",
  "field_name": "payment_schedule",
  "is_system_generated": 1,
  "modified": "2025-07-09 23:29:42.653428",
  "module": null,
  "name": "Purchase Order-payment_schedule-print_hide",
  "property": "print_hide",
  "property_type": "Check",
  "row_name": null,
  "value": "1"
 },
 {
  "default_value": null,
  "doc_type": "Purchase Invoice",
  "docstatus": 0,
  "doctype": "Property Setter",
  "doctype_or_field": "DocField",
  "field_name": "due_date",
  "is_system_generated": 1,
  "modified": "2025-07-09 23:29:42.658451",
  "module": null,
  "name": "Purchase Invoice-due_date-print_hide",
  "property": "print_hide",
  "property_type": "Check",
  "row_name": null,
  "value": "0"
 },
 {
  "default_value": null,
  "doc_type": "Purchase Invoice",
  "docstatus": 0,
  "doctype": "Property Setter",
  "doctype_or_field": "DocField",
  "field_name": "payment_schedule",
  "is_system_generated": 1,
  "modified": "2025-07-09 23:29:42.663402",
  "module": null,
  "name": "Purchase Invoice-payment_schedule-print_hide",
  "property": "print_hide",
  "property_type": "Check",
  "row_name": null,
  "value": "1"
 },
 {
  "default_value": null,
  "doc_type": "Client Script",
  "docstatus": 0,
  "doctype": "Property Setter",
  "doctype_or_field": "DocField",
  "field_name": "view",
  "is_system_generated": 1,
  "modified": "2025-07-13 14:25:35.871636",
  "module": null,
  "name": "Client Script-view-in_list_view",
  "property": "in_list_view",
  "property_type": "Check",
  "row_name": null,
  "value": "1"
 },
 {
  "default_value": null,
  "doc_type": "Client Script",
  "docstatus": 0,
  "doctype": "Property Setter",
  "doctype_or_field": "DocField",
  "field_name": "dt",
  "is_system_generated": 1,
  "modified": "2025-07-13 14:25:35.875106",
  "module": null,
  "name": "Client Script-dt-in_list_view",
  "property": "in_list_view",
  "property_type": "Check",
  "row_name": null,
  "value": "1"
 },
 {
  "default_value": null,
  "doc_type": "Client Script",
  "docstatus": 0,
  "doctype": "Property Setter",
  "doctype_or_field": "DocField",
  "field_name": "module",
  "is_system_generated": 1,
  "modified": "2025-07-13 14:25:35.876405",
  "module": null,
  "name": "Client Script-module-in_list_view",
  "property": "in_list_view",
  "property_type": "Check",
  "row_name": null,
  "value": "1"
 },
 {
  "default_value": null,
  "doc_type": "Client Script",
  "docstatus": 0,
  "doctype": "Property Setter",
  "doctype_or_field": "DocField",
  "field_name": "enabled",
  "is_system_generated": 1,
  "modified": "2025-07-13 14:25:35.877675",
  "module": null,
  "name": "Client Script-enabled-in_list_view",
  "property": "in_list_view",
  "property_type": "Check",
  "row_name": null,
  "value": "1"
 },
 {
  "default_value": null,
  "doc_type": "Employee",
  "docstatus": 0,
  "doctype": "Property Setter",
  "doctype_or_field": "DocField",
  "field_name": "naming_series",
  "is_system_generated": 1,
  "modified": "2025-07-14 20:27:28.016239",
  "module": null,
  "name": "Employee-naming_series-options",
  "property": "options",
  "property_type": "Text",
  "row_name": null,
  "value": "HR-EMP-"
 },
 {
  "default_value": null,
  "doc_type": "Employee",
  "docstatus": 0,
  "doctype": "Property Setter",
  "doctype_or_field": "DocType",
  "field_name": null,
  "is_system_generated": 0,
  "modified": "2025-07-15 14:47:21.984549",
  "module": null,
  "name": "Employee-main-title_field",
  "property": "title_field",
  "property_type": "Data",
  "row_name": null,
  "value": "employee_name"
 },
 {
  "default_value": null,
  "doc_type": "Employee",
  "docstatus": 0,
  "doctype": "Property Setter",
  "doctype_or_field": "DocType",
  "field_name": null,
  "is_system_generated": 0,
  "modified": "2025-07-15 14:47:22.032899",
  "module": null,
  "name": "Employee-main-show_title_field_in_link",
  "property": "show_title_field_in_link",
  "property_type": "Check",
  "row_name": null,
  "value": "1"
 },
 {
  "default_value": null,
  "doc_type": "Employee",
  "docstatus": 0,
  "doctype": "Property Setter",
  "doctype_or_field": "DocType",
  "field_name": null,
  "is_system_generated": 0,
  "modified": "2025-07-15 20:51:29.592812",
  "module": null,
  "name": "Employee-main-show_preview_popup",
  "property": "show_preview_popup",
  "property_type": "Check",
  "row_name": null,
  "value": "1"
 },
 {
  "default_value": null,
  "doc_type": "Employee",
  "docstatus": 0,
  "doctype": "Property Setter",
  "doctype_or_field": "DocField",
  "field_name": "employee_name",
  "is_system_generated": 0,
  "modified": "2025-07-15 20:51:29.641052",
  "module": null,
  "name": "Employee-employee_name-in_preview",
  "property": "in_preview",
  "property_type": "Check",
  "row_name": null,
  "value": "1"
 },
 {
  "default_value": "מזוהה",
  "doc_type": "Lead",
  "docstatus": 0,
  "doctype": "Property Setter",
  "doctype_or_field": "DocField",
  "field_name": "status",
  "is_system_generated": 0,
  "modified": "2025-07-16 16:38:52.878479",
  "module": "rb",
  "name": "Lead-status-options",
  "property": "options",
  "property_type": null,
  "row_name": null,
  "value": "מזוהה\nבתיאום\nממתין לאישור\nאושר\nלא מעוניין"
 },
 {
  "default_value": null,
  "doc_type": "Lead",
  "docstatus": 0,
  "doctype": "Property Setter",
  "doctype_or_field": "DocField",
  "field_name": "status",
  "is_system_generated": 0,
  "modified": "2025-07-16 16:39:12.411877",
  "module": null,
  "name": "Lead-status-default",
  "property": "default",
  "property_type": "Text",
  "row_name": null,
  "value": "מזוהה"
 },
 {
  "default_value": null,
  "doc_type": "Lead",
  "docstatus": 0,
  "doctype": "Property Setter",
  "doctype_or_field": "DocField",
  "field_name": "website",
  "is_system_generated": 0,
  "modified": "2025-07-16 16:40:08.501830",
  "module": null,
  "name": "Lead-website-hidden",
  "property": "hidden",
  "property_type": "Check",
  "row_name": null,
  "value": "1"
 },
 {
  "default_value": null,
  "doc_type": "Lead",
  "docstatus": 0,
  "doctype": "Property Setter",
  "doctype_or_field": "DocField",
  "field_name": "whatsapp_no",
  "is_system_generated": 0,
  "modified": "2025-07-16 16:40:08.534862",
  "module": null,
  "name": "Lead-whatsapp_no-hidden",
  "property": "hidden",
  "property_type": "Check",
  "row_name": null,
  "value": "1"
 },
 {
  "default_value": null,
  "doc_type": "Lead",
  "docstatus": 0,
  "doctype": "Property Setter",
  "doctype_or_field": "DocField",
  "field_name": "organization_section",
  "is_system_generated": 0,
  "modified": "2025-07-16 16:40:08.557952",
  "module": null,
  "name": "Lead-organization_section-hidden",
  "property": "hidden",
  "property_type": "Check",
  "row_name": null,
  "value": "1"
 },
 {
  "default_value": null,
  "doc_type": "Lead",
  "docstatus": 0,
  "doctype": "Property Setter",
  "doctype_or_field": "DocField",
  "field_name": "address_section",
  "is_system_generated": 0,
  "modified": "2025-07-16 16:42:44.091438",
  "module": null,
  "name": "Lead-address_section-hidden",
  "property": "hidden",
  "property_type": "Check",
  "row_name": null,
  "value": "1"
 },
 {
  "default_value": null,
  "doc_type": "Lead",
  "docstatus": 0,
  "doctype": "Property Setter",
  "doctype_or_field": "DocField",
  "field_name": "qualification_tab",
  "is_system_generated": 0,
  "modified": "2025-07-16 16:42:44.128010",
  "module": null,
  "name": "Lead-qualification_tab-hidden",
  "property": "hidden",
  "property_type": "Check",
  "row_name": null,
  "value": "1"
 },
 {
  "default_value": null,
  "doc_type": "Lead",
  "docstatus": 0,
  "doctype": "Property Setter",
  "doctype_or_field": "DocField",
  "field_name": "other_info_tab",
  "is_system_generated": 0,
  "modified": "2025-07-16 16:43:11.410291",
  "module": null,
  "name": "Lead-other_info_tab-hidden",
  "property": "hidden",
  "property_type": "Check",
  "row_name": null,
  "value": "1"
 },
 {
  "default_value": null,
  "doc_type": "Lead",
  "docstatus": 0,
  "doctype": "Property Setter",
  "doctype_or_field": "DocType",
  "field_name": null,
  "is_system_generated": 0,
  "modified": "2025-07-16 16:44:58.797064",
  "module": null,
  "name": "Lead-main-field_order",
  "property": "field_order",
  "property_type": "Data",
  "row_name": null,
  "value": "[\"naming_series\", \"salutation\", \"first_name\", \"middle_name\", \"last_name\", \"identification_number\", \"column_break_1\", \"lead_name\", \"job_title\", \"gender\", \"source\", \"cluster\", \"col_break123\", \"lead_owner\", \"status\", \"customer\", \"type\", \"request_type\", \"contact_info_tab\", \"email_id\", \"website\", \"column_break_20\", \"mobile_no\", \"whatsapp_no\", \"column_break_16\", \"phone\", \"phone_ext\", \"organization_section\", \"company_name\", \"no_of_employees\", \"column_break_28\", \"annual_revenue\", \"industry\", \"market_segment\", \"column_break_31\", \"territory\", \"fax\", \"address_section\", \"address_html\", \"column_break_38\", \"city\", \"state\", \"country\", \"column_break2\", \"contact_html\", \"qualification_tab\", \"qualification_status\", \"column_break_64\", \"qualified_by\", \"qualified_on\", \"other_info_tab\", \"campaign_name\", \"company\", \"column_break_22\", \"language\", \"image\", \"title\", \"column_break_50\", \"disabled\", \"unsubscribed\", \"blog_subscriber\", \"activities_tab\", \"open_activities_html\", \"all_activities_section\", \"all_activities_html\", \"notes_tab\", \"notes_html\", \"notes\", \"dashboard_tab\"]"
 }
]